hw_1_berezhko/__init__.py
hw_1_berezhko/main.py
hw_1_berezhko-0.0.1.dist-info/METADATA
hw_1_berezhko-0.0.1.dist-info/WHEEL
hw_1_berezhko-0.0.1.dist-info/top_level.txt
hw_1_berezhko-0.0.1.dist-info/RECORD
