Metadata-Version: 2.1
Name: hw_1_berezhko
Version: 0.0.1
Summary: Python HW 1
Author: Ekaterina Berezhko
Classifier: Programming Language :: Python :: 3
Classifier: License :: OSI Approved :: MIT License
Classifier: Operating System :: OS Independent
Requires-Python: >=3.7
